django_chile_cities/__init__.py
django_chile_cities/admin.py
django_chile_cities/apps.py
django_chile_cities/factories.py
django_chile_cities/models.py
django_chile_cities/tests.py
django_chile_cities/views.py
django_chile_cities/fixtures/city.json
django_chile_cities/fixtures/province.json
django_chile_cities/fixtures/region.json
django_chile_cities/management/__init__.py
django_chile_cities/management/commands/__init__.py
django_chile_cities/management/commands/load_chile_cities.py
django_chile_cities/migrations/0001_initial.py
django_chile_cities/migrations/__init__.py
tests_project/__init__.py
tests_project/manage.py
tests_project/tests_project/__init__.py
tests_project/tests_project/asgi.py
tests_project/tests_project/settings.py
tests_project/tests_project/urls.py
tests_project/tests_project/wsgi.py
django_chile_cities-1.0.1.dist-info/LICENSE
django_chile_cities-1.0.1.dist-info/METADATA
django_chile_cities-1.0.1.dist-info/WHEEL
django_chile_cities-1.0.1.dist-info/top_level.txt
django_chile_cities-1.0.1.dist-info/RECORD
